setup.py
discomusic/__init__.py
discomusic/discomusic.py
discomusic.egg-info/PKG-INFO
discomusic.egg-info/SOURCES.txt
discomusic.egg-info/dependency_links.txt
discomusic.egg-info/top_level.txt