Metadata-Version: 2.1
Name: discomusic
Version: 0.0.1
Summary: This is the perfect library for creating a music player discord bot!
Author: crzydev
